{
  "publicPath": "/_nuxt/",
  "all": [
    "pages/download.e3cb2d050f2068358fb0.js",
    "pages/join.c1948643be03abc971df.js",
    "pages/index.b187968c7a966c2ec3df.js",
    "layouts/default.deb3d807650b5dceeb9e.js",
    "vendor.3611d9d2b88eaa2ee1d0.js",
    "app.41e0c5a83ff20268c08a.js",
    "manifest.cee21f83be4d9c353edd.js",
    "LICENSES",
    "index.spa.html",
    "index.ssr.html"
  ],
  "initial": [
    "manifest.cee21f83be4d9c353edd.js",
    "vendor.3611d9d2b88eaa2ee1d0.js",
    "app.41e0c5a83ff20268c08a.js"
  ],
  "async": [
    "pages/download.e3cb2d050f2068358fb0.js",
    "pages/join.c1948643be03abc971df.js",
    "pages/index.b187968c7a966c2ec3df.js",
    "layouts/default.deb3d807650b5dceeb9e.js"
  ],
  "modules": {
    "15651655": [
      4
    ],
    "17806237": [
      4
    ],
    "84309302": [
      4
    ],
    "6a9dfb04": [
      4
    ],
    "cb27694a": [
      4
    ],
    "1895d81f": [
      2
    ],
    "23955e30": [
      5
    ],
    "1b641ebd": [
      4
    ],
    "d83bbce6": [
      4
    ],
    "495fb965": [
      3
    ],
    "4a688c7d": [
      0
    ],
    "22ffaaae": [
      4
    ],
    "fb89988e": [
      4
    ],
    "53b49d4e": [
      0
    ],
    "59bf7542": [
      4
    ],
    "eeec4a08": [
      2
    ],
    "2ebb0088": [
      3
    ],
    "c2be4bc0": [
      4
    ],
    "5fc2d7f0": [
      1
    ],
    "1c7f43e7": [
      4
    ],
    "454da90f": [
      4
    ],
    "d7324142": [
      5
    ],
    "15cf5ec7": [
      4
    ],
    "1002e82e": [
      4
    ],
    "7ff265fa": [
      3
    ],
    "5238ac1e": [
      4
    ],
    "1add7a72": [
      4
    ],
    "c7d23a3c": [
      5
    ],
    "71ac2a4a": [
      4
    ],
    "4174bbc0": [
      5
    ],
    "5efefd92": [
      4
    ],
    "85031e82": [
      5
    ],
    "bfb5d35a": [
      4
    ],
    "0452f5b3": [
      4
    ],
    "006110c5": [
      4
    ],
    "9e77f278": [
      5
    ],
    "e71ea5a8": [
      4
    ],
    "586f8d08": [
      4
    ],
    "4b5d066a": [
      4
    ],
    "894f9ca4": [
      4
    ],
    "5c953956": [
      4
    ],
    "2446c186": [
      2
    ],
    "25dc60cd": [
      4
    ],
    "0435912c": [
      4
    ],
    "ab3ea372": [
      4
    ],
    "e0f6e600": [
      5
    ],
    "e809c370": [
      4
    ],
    "99abbb1a": [
      4
    ],
    "78744f42": [
      4
    ],
    "92f987b2": [
      4
    ],
    "d49d474c": [
      4
    ],
    "71bd3aee": [
      4
    ],
    "1c538863": [
      4
    ],
    "5dee75df": [
      4
    ],
    "8f0126dc": [
      4
    ],
    "7152b8ae": [
      4
    ],
    "203e5e24": [
      5
    ],
    "dc40df3a": [
      4
    ],
    "4fe2428e": [
      4
    ],
    "2e43946d": [
      4
    ],
    "537d9664": [
      4
    ],
    "789c3163": [
      4
    ],
    "2d7d657d": [
      4
    ],
    "15c16436": [
      4
    ],
    "5b32b481": [
      4
    ],
    "32f08104": [
      4
    ],
    "638d0da4": [
      5
    ],
    "6ce97a11": [
      4
    ],
    "6f18f61e": [
      4
    ],
    "04ae7de8": [
      0
    ],
    "0cb6be9d": [
      5
    ],
    "6a04e936": [
      4
    ],
    "91769af8": [
      0
    ],
    "353c5760": [
      4
    ],
    "098bb861": [
      4
    ],
    "5dc33264": [
      4
    ],
    "fa6a33d4": [
      4
    ],
    "3c7a7dee": [
      4
    ],
    "bc32fbf0": [
      4
    ],
    "b5b78fee": [
      4
    ],
    "3d8f9862": [
      4
    ],
    "221d3dd6": [
      4
    ],
    "56df1abe": [
      4
    ],
    "0aa8efc0": [
      4
    ],
    "327efaec": [
      5
    ],
    "b1d0ae80": [
      4
    ],
    "ab4f1326": [
      4
    ],
    "6c1872d8": [
      4
    ],
    "65ffb633": [
      4
    ],
    "0b41e034": [
      5
    ],
    "b0422f24": [
      4
    ],
    "719c68a3": [
      5
    ],
    "a73819b6": [
      3
    ],
    "d89919f8": [
      4
    ],
    "414f1826": [
      4
    ],
    "1d6699c2": [
      4
    ],
    "71cade10": [
      4
    ],
    "23c9290c": [
      4
    ],
    "eab7c422": [
      4
    ],
    "7357df9a": [
      4
    ],
    "2425b592": [
      4
    ],
    "5fc017ee": [
      4
    ],
    "86f27c2e": [
      4
    ],
    "7c5e7d65": [
      4
    ],
    "50cbaa94": [
      4
    ],
    "1b19c5ac": [
      4
    ],
    "cbc4b1b0": [
      4
    ],
    "89c6da3e": [
      4
    ],
    "c7d2129e": [
      4
    ],
    "76d289da": [
      4
    ],
    "362fba26": [
      4
    ],
    "598afc55": [
      4
    ],
    "14b066e4": [
      4
    ],
    "471d72f6": [
      0
    ],
    "1fb62954": [
      4
    ],
    "3b0350c5": [
      4
    ],
    "7a31a4cb": [
      4
    ],
    "0b2d51f7": [
      4
    ],
    "b6891980": [
      4
    ],
    "f72272da": [
      4
    ],
    "13b9f8a3": [
      4
    ],
    "2ca0d611": [
      4
    ],
    "70ddd034": [
      1
    ],
    "15ba65ef": [
      4
    ],
    "95b66078": [
      5
    ],
    "6865b0f9": [
      4
    ],
    "5001893c": [
      4
    ],
    "5109726e": [
      4
    ],
    "3954b724": [
      4
    ],
    "5c574fa4": [
      5
    ],
    "0a201998": [
      4
    ],
    "b4b8ccf8": [
      4
    ],
    "04e3e89c": [
      5
    ],
    "c9eaf93e": [
      4
    ],
    "2a944b02": [
      4
    ],
    "b93dc91e": [
      4
    ],
    "4d654d2e": [
      4
    ],
    "4d87216a": [
      4
    ],
    "0b3ce174": [
      5
    ],
    "1ebb2ee3": [
      4
    ],
    "ea07e890": [
      5
    ],
    "859cf754": [
      4
    ],
    "e468933e": [
      4
    ],
    "87e7c33a": [
      4
    ],
    "b4006aea": [
      4
    ],
    "35b0c9ea": [
      4
    ],
    "0741293d": [
      4
    ],
    "791bb2a7": [
      4
    ],
    "6dcada88": [
      4
    ],
    "1d6934d7": [
      4
    ],
    "00edf4e8": [
      4
    ],
    "3cf4b305": [
      4
    ],
    "10ad2b36": [
      4
    ],
    "170bcb58": [
      4
    ],
    "762ec7a2": [
      4
    ],
    "cba60692": [
      4
    ],
    "6b62117d": [
      5
    ],
    "017a94dd": [
      5
    ],
    "8252865a": [
      4
    ],
    "109f825c": [
      5
    ],
    "b0557c2c": [
      4
    ],
    "6f3321b1": [
      4
    ],
    "3325bd6e": [
      4
    ],
    "1bf33e2e": [
      4
    ],
    "aa2c3af0": [
      4
    ],
    "1ee45610": [
      4
    ],
    "85f56eea": [
      4
    ],
    "441f4b42": [
      0
    ],
    "6fcfbdb4": [
      4
    ],
    "71de8f30": [
      4
    ],
    "ebaea640": [
      4
    ],
    "2e2c0fb4": [
      1
    ],
    "5d04f3a5": [
      4
    ],
    "66217dcf": [
      4
    ],
    "3df7bc44": [
      4
    ],
    "2c4dca86": [
      5
    ],
    "421bb0be": [
      4
    ],
    "1eed23b0": [
      4
    ],
    "71c1c6a4": [
      4
    ],
    "39cfe817": [
      4
    ],
    "ba591e56": [
      4
    ],
    "586fa65e": [
      4
    ],
    "f6536dbe": [
      4
    ],
    "2d8ef3a2": [
      4
    ],
    "1a50eb92": [
      4
    ],
    "f09aa516": [
      4
    ],
    "582d01a1": [
      4
    ],
    "a60f7f26": [
      5
    ],
    "4baef233": [
      4
    ],
    "6b625990": [
      4
    ],
    "1e20a4e8": [
      4
    ],
    "c09fab9e": [
      4
    ],
    "184a42e0": [
      4
    ],
    "b428514e": [
      4
    ],
    "e10de8f8": [
      4
    ],
    "192fb7ce": [
      4
    ],
    "1bab05b4": [
      4
    ],
    "3314bb9d": [
      5
    ],
    "6472e5d8": [
      4
    ],
    "20cdbe0d": [
      4
    ],
    "58811fd2": [
      4
    ],
    "7125f36d": [
      4
    ],
    "3e7e12aa": [
      4
    ],
    "4b4ac10a": [
      4
    ],
    "1e178e5a": [
      4
    ],
    "dde5b5ac": [
      4
    ],
    "a270ed22": [
      4
    ],
    "0f97693a": [
      4
    ],
    "67523cee": [
      4
    ],
    "5ad1a6de": [
      5
    ],
    "541111b9": [
      4
    ],
    "274e84f4": [
      4
    ],
    "efffeb6e": [
      5
    ]
  }
}